README.md
setup.cfg
setup.py
pyblink/__init__.py
pyblink/run.py
pyblink/util.py
pyblink.egg-info/PKG-INFO
pyblink.egg-info/SOURCES.txt
pyblink.egg-info/dependency_links.txt
pyblink.egg-info/entry_points.txt
pyblink.egg-info/requires.txt
pyblink.egg-info/top_level.txt
pyblink/image/__init__.py
pyblink/image/build_image.py
pyblink/image/startup_script.sh