Metadata-Version: 1.0
Name: pyblink
Version: 0.1.0
Summary: Compute in a blink with Google Cloud Platform
Home-page: https://github.com/thooun/pyblink
Author: Thomas Ounnas
Author-email: tho.ounn@gmail.com
License: UNKNOWN
Platform: UNKNOWN
